LICENSE
MANIFEST.in
README.md
manage.py
requirements.freeze
requirements.txt
setup.py
config/__init__.py
config/asgi.py
config/urls.py
config/wsgi.py
config/settings/__init__.py
config/settings/base.py
config/settings/dev.py
config/settings/test.py
django_lessons.egg-info/PKG-INFO
django_lessons.egg-info/SOURCES.txt
django_lessons.egg-info/dependency_links.txt
django_lessons.egg-info/top_level.txt
lessons/__init__.py
lessons/admin.py
lessons/apps.py
lessons/feed.py
lessons/forms.py
lessons/models.py
lessons/tests.py
lessons/urls.py
lessons/views.py
lessons/wagtail_hooks.py
lessons/migrations/0001_initial.py
lessons/migrations/0002_lessonsindex.py
lessons/migrations/0003_lesson_order.py
lessons/migrations/0004_auto_20200205_0545.py
lessons/migrations/0005_auto_20200205_0604.py
lessons/migrations/0006_auto_20200205_0640.py
lessons/migrations/0007_auto_20200205_0707.py
lessons/migrations/0008_lessontagindex.py
lessons/migrations/0009_lesson_script.py
lessons/migrations/__init__.py
lessons/templates/admin/change_form.html
lessons/templates/lessons/500.html
lessons/templates/lessons/_right_sidebar.html
lessons/templates/lessons/about.html
lessons/templates/lessons/base.html
lessons/templates/lessons/cookies.html
lessons/templates/lessons/impressum.html
lessons/templates/lessons/index.html
lessons/templates/lessons/lesson.html
lessons/templates/lessons/lesson_tag_index.html
lessons/templates/lessons/privacy.html
lessons/templates/lessons/subscribe.html
lessons/templates/lessons/thankyou.html
lessons/templates/lessons/blocks/code.html
lessons/templates/lessons/notify_subscribers/email.html
lessons/templates/lessons/notify_subscribers/email.txt