Metadata-Version: 1.0
Name: django-lessons
Version: 1.0.0
Summary: Web based application to host django lessons
Home-page: https://www.django-lessons.com/
Author: Eugen Ciur
Author-email: eugen@django-lessons.com
License: Apache 2.0 License
Platform: UNKNOWN
